apricotpy/__init__.py
apricotpy/event_loop.py
apricotpy/events.py
apricotpy/futures.py
apricotpy/messages.py
apricotpy/objects.py
apricotpy/persistence.py
apricotpy/tasks.py
apricotpy/utils.py
apricotpy-0.1.0.dev1.dist-info/DESCRIPTION.rst
apricotpy-0.1.0.dev1.dist-info/METADATA
apricotpy-0.1.0.dev1.dist-info/RECORD
apricotpy-0.1.0.dev1.dist-info/WHEEL
apricotpy-0.1.0.dev1.dist-info/metadata.json
apricotpy-0.1.0.dev1.dist-info/top_level.txt
